{"status_code":200,"result":{"count":13,"items":[{"id":"1607020001","nama":"TAJA INDAH"},{"id":"1607020002","nama":"TAJA MULYA"},{"id":"1607020003","nama":"TAJA RAYA I"},{"id":"1607020004","nama":"PULAU RAJAK"},{"id":"1607020014","nama":"LUBUK KARET"},{"id":"1607020015","nama":"BETUNG"},{"id":"1607020016","nama":"BUKIT"},{"id":"1607020017","nama":"SRI KEMBANG"},{"id":"1607020018","nama":"TAJA RAYA II"},{"id":"1607020020","nama":"SUKA MULYA"},{"id":"1607020021","nama":"RIMBA ASAM"},{"id":"1607020022","nama":"DESA PERSIAPAN BUKIT MAKMUR"},{"id":"1607020023","nama":"BETUNG SELATAN"}]}}