{"status_code":200,"result":{"count":26,"items":[{"id":"6504030001","nama":"PAYANG"},{"id":"6504030002","nama":"SUYADON"},{"id":"6504030003","nama":"TUKULON"},{"id":"6504030004","nama":"BULU MENGOLOM"},{"id":"6504030005","nama":"BATUNG"},{"id":"6504030006","nama":"UBOL SULOK"},{"id":"6504030007","nama":"UBOL ALUNG"},{"id":"6504030008","nama":"NANSAPAN"},{"id":"6504030009","nama":"SEDALIT"},{"id":"6504030010","nama":"TAMBALANG HILIR"},{"id":"6504030011","nama":"PALUAN"},{"id":"6504030012","nama":"JUKUP"},{"id":"6504030013","nama":"LONG BULU"},{"id":"6504030014","nama":"KALAMBUKU"},{"id":"6504030015","nama":"TADUNGUS"},{"id":"6504030016","nama":"SEMATA"},{"id":"6504030017","nama":"LINSAYUNG"},{"id":"6504030018","nama":"SALAN"},{"id":"6504030019","nama":"SUNGOI"},{"id":"6504030020","nama":"SINAMPILA I"},{"id":"6504030021","nama":"SAMUNTI"},{"id":"6504030022","nama":"SINAMPILA II"},{"id":"6504030023","nama":"LIMPAKON"},{"id":"6504030024","nama":"LABUK"},{"id":"6504030026","nama":"SANAL"},{"id":"6504030027","nama":"TUMANTALAS"}]}}