{"status_code":200,"result":{"count":21,"items":[{"id":"9606080001","nama":"HUGITAPA"},{"id":"9606080002","nama":"WAIAGEPA"},{"id":"9606080003","nama":"KOBAE"},{"id":"9606080004","nama":"MAPA"},{"id":"9606080005","nama":"OGEAPA"},{"id":"9606080006","nama":"BONOGO"},{"id":"9606080007","nama":"HIYABU"},{"id":"9606080008","nama":"MAYA"},{"id":"9606080009","nama":"NGGAGEMPA"},{"id":"9606080010","nama":"BILAI I"},{"id":"9606080011","nama":"AGAPA"},{"id":"9606080012","nama":"ENGGANENGA"},{"id":"9606080013","nama":"DEGESIGA"},{"id":"9606080014","nama":"POGAPA"},{"id":"9606080015","nama":"BILAI DUA"},{"id":"9606080016","nama":"ZOMBAN DOGA"},{"id":"9606080017","nama":"BUBISIGA"},{"id":"9606080018","nama":"SELEMAMA"},{"id":"9606080019","nama":"KENDETAPA"},{"id":"9606080020","nama":"MBOMOGO"},{"id":"9606080021","nama":"SANEPA"}]}}