{"status_code":200,"result":{"count":22,"items":[{"id":"9608180001","nama":"TINGGINERI"},{"id":"9608180002","nama":"MONIA"},{"id":"9608180003","nama":"TINGGINAMBUT"},{"id":"9608180004","nama":"MELEKOM"},{"id":"9608180005","nama":"GUBUGUR"},{"id":"9608180006","nama":"BERIME"},{"id":"9608180007","nama":"WOMELAGANDAN"},{"id":"9608180008","nama":"TOMBO"},{"id":"9608180009","nama":"GIMANGGEN"},{"id":"9608180010","nama":"URAGI"},{"id":"9608180011","nama":"YAMENGGA"},{"id":"9608180012","nama":"DEGI"},{"id":"9608180013","nama":"PARALO"},{"id":"9608180014","nama":"YUGUMBELAWI"},{"id":"9608180015","nama":"BIGIRAGE"},{"id":"9608180016","nama":"LUMBUK"},{"id":"9608180017","nama":"INIKIMALUK"},{"id":"9608180018","nama":"GOBAK"},{"id":"9608180019","nama":"PAPUA"},{"id":"9608180020","nama":"TINGGINIME"},{"id":"9608180021","nama":"GIGUME"},{"id":"9608180022","nama":"YONGGUN"}]}}