{"status_code":200,"result":{"count":13,"items":[{"id":"9707160001","nama":"YALISOMON"},{"id":"9707160002","nama":"YABI"},{"id":"9707160003","nama":"HAMIK"},{"id":"9707160004","nama":"KULAHAIK"},{"id":"9707160005","nama":"SOBAHAM"},{"id":"9707160006","nama":"BALINGGAMA"},{"id":"9707160007","nama":"DOHONG"},{"id":"9707160008","nama":"SIMBUK"},{"id":"9707160009","nama":"PUAHUN"},{"id":"9707160010","nama":"SILAK PAHABOL"},{"id":"9707160011","nama":"SELE"},{"id":"9707160012","nama":"BENEMBIA"},{"id":"9707160013","nama":"HUBIK"}]}}